LICENCE.txt
MANIFEST.in
README.txt
setup.py
crypto_math_utils/__init__.py.py
crypto_math_utils.egg-info/PKG-INFO
crypto_math_utils.egg-info/SOURCES.txt
crypto_math_utils.egg-info/dependency_links.txt
crypto_math_utils.egg-info/top_level.txt