Metadata-Version: 2.1
Name: crypto-math-utils
Version: 0.0.1
Summary: Computes the coefficient of Bezouts identity
Home-page: 
Author: Pratyush Prasad Sahoo
Author-email: prats.sahoo2k22@gmail.com
License: MIT
Keywords: gcd bezouts euclidean
Classifier: Development Status :: 5 - Production/Stable
Classifier: Intended Audience :: Education
Classifier: Operating System :: Microsoft :: Windows :: Windows 11
Classifier: License :: OSI Approved :: MIT License
Classifier: Programming Language :: Python :: 3
License-File: LICENCE.txt
